hssadmin
