Metadata-Version: 1.1
Name: hssadmin
Version: 0.3.1
Summary: Cloudian HyperStore(R) Admin API SDK for Python
Home-page: https://github.com/ryosuke-mt/hyperstore
Author: Ryosuke Matsui
Author-email: rmatsui@cloudian.com
License: MIT
Keywords: sample setuptools development
Platform: UNKNOWN
Classifier: Programming Language :: Python :: 3.3
Classifier: Programming Language :: Python :: 3.4
Classifier: Programming Language :: Python :: 3.5
Classifier: Programming Language :: Python :: 3.6
Classifier: License :: OSI Approved :: MIT License
